[
  {
    "title": "HTML",
    "imageSrc": "skills/html.png"
  },
  {
    "title": "CSS",
    "imageSrc": "skills/css.png"
  },
  {
    "title": "React",
    "imageSrc": "skills/react.png"
  },
  {
    "title": "Javascript",
    "imageSrc": "skills/node.png"
  },
  {
    "title": "Python",
    "imageSrc": "skills/graphql.png"
  },
  {
    "title": "Github",
    "imageSrc": "skills/github.png"
  },
  {
    "title": "DSA",
    "imageSrc": "skills/figma.png"
  },
  {
    "title": "Mongodb",
    "imageSrc": "skills/mongo.png"
  },
  {
    "title": "Node.js",
    "imageSrc": "skills/nodeJS.png"
  }
]